nsfr750_pybench-1.3.0.dist-info/licenses/LICENSE
script/__init__.py
script/about.py
script/config_manager.py
script/help.py
script/lang_mgr.py
script/log_viewer.py
script/logger.py
script/new_menu.py
script/settings.py
script/sponsor.py
script/theme_manager.py
script/translations.py
script/updates.py
script/version.py
script/view_log.py
script/visualization.py
script/test_script/CLI_pystone.py
script/test_script/__init__.py
script/test_script/benchmark_history.py
script/test_script/benchmark_tests.py
script/test_script/export_dialog.py
script/test_script/export_results.py
script/test_script/hardware_monitor.py
script/test_script/history_dialog.py
script/test_script/pystone_dialog.py
script/test_script/pystone_test.py
script/test_script/system_info.py
script/test_script/test_benchmark.py
script/test_script/test_hardware_monitor.py
script/test_script/test_monitor.py
tests/TEST_README.md
tests/test_monitor_manual.py
nsfr750_pybench-1.3.0.dist-info/METADATA
nsfr750_pybench-1.3.0.dist-info/WHEEL
nsfr750_pybench-1.3.0.dist-info/entry_points.txt
nsfr750_pybench-1.3.0.dist-info/top_level.txt
nsfr750_pybench-1.3.0.dist-info/RECORD
