Metadata-Version: 2.4
Name: nsfr750-pybench
Version: 1.3.0
Summary: A comprehensive benchmarking tool with a modern GUI
Home-page: https://github.com/Nsfr750/benchmark
Author: Nsfr750
Author-email: nsfr750@yandex.com
License: GPLv3
Project-URL: Bug Reports, https://github.com/Nsfr750/benchmark/issues
Project-URL: Source, https://github.com/Nsfr750/benchmark
Project-URL: Documentation, https://github.com/Nsfr750/benchmark/wiki
Keywords: benchmark system performance monitoring
Classifier: Development Status :: 4 - Beta
Classifier: Intended Audience :: Developers
Classifier: Intended Audience :: Information Technology
Classifier: Intended Audience :: System Administrators
Classifier: License :: OSI Approved :: GNU General Public License v3 (GPLv3)
Classifier: Operating System :: Microsoft :: Windows :: Windows 10
Classifier: Operating System :: Microsoft :: Windows :: Windows 11
Classifier: Programming Language :: Python :: 3.8
Classifier: Programming Language :: Python :: 3.9
Classifier: Programming Language :: Python :: 3.10
Classifier: Programming Language :: Python :: 3.11
Classifier: Topic :: System :: Benchmark
Classifier: Topic :: System :: Monitoring
Classifier: Topic :: System :: Systems Administration
Classifier: Topic :: Utilities
Requires-Python: >=3.8
License-File: LICENSE
Requires-Dist: PySide6<7.0.0,>=6.5.0
Requires-Dist: wand<0.7.0,>=0.6.10
Requires-Dist: pywin32<308,>=306; platform_system == "Windows"
Requires-Dist: psutil<6.0.0,>=5.9.5
Requires-Dist: py-cpuinfo<10.0.0,>=9.0.0
Requires-Dist: wmi<2.0.0,>=1.5.1; platform_system == "Windows"
Requires-Dist: numpy<3.0.0,>=2.0.2
Requires-Dist: pandas<3.0.0,>=2.0.0
Requires-Dist: matplotlib<4.0.0,>=3.7.0
Requires-Dist: requests<3.0.0,>=2.31.0
Requires-Dist: python-dateutil<3.0.0,>=2.8.2
Provides-Extra: dev
Requires-Dist: pytest<8.0.0,>=7.0.0; extra == "dev"
Requires-Dist: pytest-cov<5.0.0,>=4.0.0; extra == "dev"
Requires-Dist: black<24.0.0,>=23.0.0; extra == "dev"
Requires-Dist: flake8<7.0.0,>=6.0.0; extra == "dev"
Requires-Dist: mypy<2.0.0,>=1.0.0; extra == "dev"
Requires-Dist: isort<6.0.0,>=5.12.0; extra == "dev"
Dynamic: author
Dynamic: author-email
Dynamic: classifier
Dynamic: description
Dynamic: description-content-type
Dynamic: home-page
Dynamic: keywords
Dynamic: license
Dynamic: license-file
Dynamic: project-url
Dynamic: provides-extra
Dynamic: requires-dist
Dynamic: requires-python
Dynamic: summary
